setup.py
djangox/__init__.py
djangox/route/__init__.py
djangox_route.egg-info/PKG-INFO
djangox_route.egg-info/SOURCES.txt
djangox_route.egg-info/dependency_links.txt
djangox_route.egg-info/namespace_packages.txt
djangox_route.egg-info/top_level.txt