Metadata-Version: 1.1
Name: djangox-route
Version: 0.0.4
Summary: Discover django views and register to urlconf by convention.
Home-page: https://github.com/youngrok/djangox-route
Author: Youngrok Pak
Author-email: pak.youngrok@gmail.com
License: UNKNOWN
Keywords: rest route autodiscover django djangox
Platform: UNKNOWN
Classifier: Development Status :: 3 - Alpha
Classifier: Topic :: Software Development :: Libraries
Classifier: License :: OSI Approved :: BSD License
